{
  "type": "FeatureCollection",
  "features": [
    {
      "type": "Feature",
      "properties": {
        "名称": "Cages",
        "球桌": "Fireball",
        "地址": "静安体育中心, 江宁路428号3楼, 近武定路",
        "点评": "https://www.dianping.com/shop/kaZ9w7q97FohyYfc"
      },
      "geometry": {
        "type": "Point",
        "coordinates": [
          116.40335,
          39.94069
        ]
      }
    },
    {
      "type": "Feature",
      "properties": {
        "名称": "Park 91 Pub",
        "球桌": "Fireball",
        "地址": "上海市静安区大沽路433号, 近成都路",
        "点评": "https://www.dianping.com/shop/l8oqvgwIMOicHd59"
      },
      "geometry": {
        "type": "Point",
        "coordinates": [
          121.46581,
          31.22535
        ]
      }
    }
  ]
}
